currency_markdown
